<?xml version="1.0" encoding="UTF-8" standalone="yes"?>
<p:sld xmlns:a="http://schemas.openxmlformats.org/drawingml/2006/main" xmlns:r="http://schemas.openxmlformats.org/officeDocument/2006/relationships" xmlns:p="http://schemas.openxmlformats.org/presentationml/2006/main"><p:cSld><p:spTree><p:nvGrpSpPr><p:cNvPr id="1" name=""/><p:cNvGrpSpPr/><p:nvPr/></p:nvGrpSpPr><p:grpSpPr><a:xfrm><a:off x="0" y="0"/><a:ext cx="0" cy="0"/><a:chOff x="0" y="0"/><a:chExt cx="0" cy="0"/></a:xfrm></p:grpSpPr><p:pic><p:nvPicPr><p:cNvPr id="16" name="Amarantos"><a:hlinkClick r:id="" action="ppaction://media"/><a:extLst><a:ext uri="{FF2B5EF4-FFF2-40B4-BE49-F238E27FC236}"><a16:creationId xmlns:a16="http://schemas.microsoft.com/office/drawing/2014/main" id="{601E38AD-C82F-440B-AB13-02CE1815DCD8}"/></a:ext></a:extLst></p:cNvPr><p:cNvPicPr><a:picLocks noChangeAspect="1"/></p:cNvPicPr><p:nvPr><a:audioFile r:link="rId1"/><p:extLst><p:ext uri="{DAA4B4D4-6D71-4841-9C94-3DE7FCFB9230}"><p14:media xmlns:p14="http://schemas.microsoft.com/office/powerpoint/2010/main" r:embed="rId2"><p14:trim st="8443"/></p14:media></p:ext></p:extLst></p:nvPr></p:nvPicPr><p:blipFill><a:blip r:embed="rId4"/><a:stretch><a:fillRect/></a:stretch></p:blipFill><p:spPr><a:xfrm><a:off x="4743792" y="2857500"/><a:ext cx="487363" cy="487363"/></a:xfrm><a:prstGeom prst="rect"><a:avLst/></a:prstGeom></p:spPr></p:pic><p:sp><p:nvSpPr><p:cNvPr id="2" name="Freeform 2"/><p:cNvSpPr/><p:nvPr/></p:nvSpPr><p:spPr><a:xfrm><a:off x="0" y="0"/><a:ext cx="18288000" cy="10287000"/></a:xfrm><a:custGeom><a:avLst/><a:gdLst/><a:ahLst/><a:cxnLst/><a:rect l="l" t="t" r="r" b="b"/><a:pathLst><a:path w="18288000" h="10287000"><a:moveTo><a:pt x="0" y="0"/></a:moveTo><a:lnTo><a:pt x="18288000" y="0"/></a:lnTo><a:lnTo><a:pt x="18288000" y="10287000"/></a:lnTo><a:lnTo><a:pt x="0" y="10287000"/></a:lnTo><a:lnTo><a:pt x="0" y="0"/></a:lnTo><a:close/></a:path></a:pathLst></a:custGeom><a:blipFill><a:blip r:embed="rId5"/><a:stretch><a:fillRect/></a:stretch></a:blipFill></p:spPr></p:sp><p:sp><p:nvSpPr><p:cNvPr id="3" name="Freeform 3"/><p:cNvSpPr/><p:nvPr/></p:nvSpPr><p:spPr><a:xfrm><a:off x="0" y="8052811"/><a:ext cx="6475894" cy="1610879"/></a:xfrm><a:custGeom><a:avLst/><a:gdLst/><a:ahLst/><a:cxnLst/><a:rect l="l" t="t" r="r" b="b"/><a:pathLst><a:path w="6475894" h="1610879"><a:moveTo><a:pt x="0" y="0"/></a:moveTo><a:lnTo><a:pt x="6475894" y="0"/></a:lnTo><a:lnTo><a:pt x="6475894" y="1610878"/></a:lnTo><a:lnTo><a:pt x="0" y="1610878"/></a:lnTo><a:lnTo><a:pt x="0" y="0"/></a:lnTo><a:close/></a:path></a:pathLst></a:custGeom><a:blipFill><a:blip r:embed="rId6"><a:extLst><a:ext uri="{96DAC541-7B7A-43D3-8B79-37D633B846F1}"><asvg:svgBlip xmlns:asvg="http://schemas.microsoft.com/office/drawing/2016/SVG/main" r:embed="rId7"/></a:ext></a:extLst></a:blip><a:stretch><a:fillRect/></a:stretch></a:blipFill></p:spPr></p:sp><p:sp><p:nvSpPr><p:cNvPr id="4" name="TextBox 4"/><p:cNvSpPr txBox="1"/><p:nvPr/></p:nvSpPr><p:spPr><a:xfrm><a:off x="457201" y="8512075"/><a:ext cx="5575876" cy="577081"/></a:xfrm><a:prstGeom prst="rect"><a:avLst/></a:prstGeom></p:spPr><p:txBody><a:bodyPr wrap="square" lIns="0" tIns="0" rIns="0" bIns="0" rtlCol="0" anchor="t"><a:spAutoFit/></a:bodyPr><a:lstStyle/><a:p><a:pPr algn="ctr"><a:lnSpc><a:spcPts val="4480"/></a:lnSpc></a:pPr><a:r><a:rPr lang="en-US" sz="3200" u="sng" dirty="0" err="1"><a:latin typeface=" Avenir Next Arabic"/><a:ea typeface=" Avenir Next Arabic"/><a:cs typeface=" Avenir Next Arabic"/><a:sym typeface=" Avenir Next Arabic"/><a:hlinkClick r:id="rId8" action="ppaction://hlinksldjump"><a:extLst><a:ext uri="{A12FA001-AC4F-418D-AE19-62706E023703}"><ahyp:hlinkClr xmlns:ahyp="http://schemas.microsoft.com/office/drawing/2018/hyperlinkcolor" val="tx"/></a:ext></a:extLst></a:hlinkClick></a:rPr><a:t>Entrar</a:t></a:r><a:r><a:rPr lang="en-US" sz="3200" u="sng" dirty="0"><a:latin typeface=" Avenir Next Arabic"/><a:ea typeface=" Avenir Next Arabic"/><a:cs typeface=" Avenir Next Arabic"/><a:sym typeface=" Avenir Next Arabic"/><a:hlinkClick r:id="rId8" action="ppaction://hlinksldjump"><a:extLst><a:ext uri="{A12FA001-AC4F-418D-AE19-62706E023703}"><ahyp:hlinkClr xmlns:ahyp="http://schemas.microsoft.com/office/drawing/2018/hyperlinkcolor" val="tx"/></a:ext></a:extLst></a:hlinkClick></a:rPr><a:t> pela Porta Principal</a:t></a:r></a:p></p:txBody></p:sp><p:sp><p:nvSpPr><p:cNvPr id="5" name="Freeform 5"/><p:cNvSpPr/><p:nvPr/></p:nvSpPr><p:spPr><a:xfrm><a:off x="11970596" y="8052811"/><a:ext cx="6475894" cy="1610879"/></a:xfrm><a:custGeom><a:avLst/><a:gdLst/><a:ahLst/><a:cxnLst/><a:rect l="l" t="t" r="r" b="b"/><a:pathLst><a:path w="6475894" h="1610879"><a:moveTo><a:pt x="0" y="0"/></a:moveTo><a:lnTo><a:pt x="6475894" y="0"/></a:lnTo><a:lnTo><a:pt x="6475894" y="1610878"/></a:lnTo><a:lnTo><a:pt x="0" y="1610878"/></a:lnTo><a:lnTo><a:pt x="0" y="0"/></a:lnTo><a:close/></a:path></a:pathLst></a:custGeom><a:blipFill><a:blip r:embed="rId6"><a:extLst><a:ext uri="{96DAC541-7B7A-43D3-8B79-37D633B846F1}"><asvg:svgBlip xmlns:asvg="http://schemas.microsoft.com/office/drawing/2016/SVG/main" r:embed="rId7"/></a:ext></a:extLst></a:blip><a:stretch><a:fillRect/></a:stretch></a:blipFill></p:spPr></p:sp><p:sp><p:nvSpPr><p:cNvPr id="6" name="TextBox 6"/><p:cNvSpPr txBox="1"/><p:nvPr/></p:nvSpPr><p:spPr><a:xfrm><a:off x="12670286" y="8551228"/><a:ext cx="5312914" cy="577081"/></a:xfrm><a:prstGeom prst="rect"><a:avLst/></a:prstGeom></p:spPr><p:txBody><a:bodyPr wrap="square" lIns="0" tIns="0" rIns="0" bIns="0" rtlCol="0" anchor="t"><a:spAutoFit/></a:bodyPr><a:lstStyle/><a:p><a:pPr algn="ctr"><a:lnSpc><a:spcPts val="4480"/></a:lnSpc></a:pPr><a:r><a:rPr lang="en-US" sz="3200" u="sng" dirty="0" err="1"><a:latin typeface=" Avenir Next Arabic"/><a:ea typeface=" Avenir Next Arabic"/><a:cs typeface=" Avenir Next Arabic"/><a:sym typeface=" Avenir Next Arabic"/><a:hlinkClick r:id="rId9" action="ppaction://hlinksldjump"><a:extLst><a:ext uri="{A12FA001-AC4F-418D-AE19-62706E023703}"><ahyp:hlinkClr xmlns:ahyp="http://schemas.microsoft.com/office/drawing/2018/hyperlinkcolor" val="tx"/></a:ext></a:extLst></a:hlinkClick></a:rPr><a:t>Entrar</a:t></a:r><a:r><a:rPr lang="en-US" sz="3200" u="sng" dirty="0"><a:latin typeface=" Avenir Next Arabic"/><a:ea typeface=" Avenir Next Arabic"/><a:cs typeface=" Avenir Next Arabic"/><a:sym typeface=" Avenir Next Arabic"/><a:hlinkClick r:id="rId9" action="ppaction://hlinksldjump"><a:extLst><a:ext uri="{A12FA001-AC4F-418D-AE19-62706E023703}"><ahyp:hlinkClr xmlns:ahyp="http://schemas.microsoft.com/office/drawing/2018/hyperlinkcolor" val="tx"/></a:ext></a:extLst></a:hlinkClick></a:rPr><a:t> pela </a:t></a:r><a:r><a:rPr lang="en-US" sz="3200" u="sng" dirty="0" err="1"><a:latin typeface=" Avenir Next Arabic"/><a:ea typeface=" Avenir Next Arabic"/><a:cs typeface=" Avenir Next Arabic"/><a:sym typeface=" Avenir Next Arabic"/><a:hlinkClick r:id="rId9" action="ppaction://hlinksldjump"><a:extLst><a:ext uri="{A12FA001-AC4F-418D-AE19-62706E023703}"><ahyp:hlinkClr xmlns:ahyp="http://schemas.microsoft.com/office/drawing/2018/hyperlinkcolor" val="tx"/></a:ext></a:extLst></a:hlinkClick></a:rPr><a:t>uma</a:t></a:r><a:r><a:rPr lang="en-US" sz="3200" u="sng" dirty="0"><a:latin typeface=" Avenir Next Arabic"/><a:ea typeface=" Avenir Next Arabic"/><a:cs typeface=" Avenir Next Arabic"/><a:sym typeface=" Avenir Next Arabic"/><a:hlinkClick r:id="rId9" action="ppaction://hlinksldjump"><a:extLst><a:ext uri="{A12FA001-AC4F-418D-AE19-62706E023703}"><ahyp:hlinkClr xmlns:ahyp="http://schemas.microsoft.com/office/drawing/2018/hyperlinkcolor" val="tx"/></a:ext></a:extLst></a:hlinkClick></a:rPr><a:t> </a:t></a:r><a:r><a:rPr lang="en-US" sz="3200" u="sng" dirty="0" err="1"><a:latin typeface=" Avenir Next Arabic"/><a:ea typeface=" Avenir Next Arabic"/><a:cs typeface=" Avenir Next Arabic"/><a:sym typeface=" Avenir Next Arabic"/><a:hlinkClick r:id="rId9" action="ppaction://hlinksldjump"><a:extLst><a:ext uri="{A12FA001-AC4F-418D-AE19-62706E023703}"><ahyp:hlinkClr xmlns:ahyp="http://schemas.microsoft.com/office/drawing/2018/hyperlinkcolor" val="tx"/></a:ext></a:extLst></a:hlinkClick></a:rPr><a:t>janela</a:t></a:r><a:endParaRPr lang="en-US" sz="3200" u="sng" dirty="0"><a:latin typeface=" Avenir Next Arabic"/><a:ea typeface=" Avenir Next Arabic"/><a:cs typeface=" Avenir Next Arabic"/><a:sym typeface=" Avenir Next Arabic"/><a:hlinkClick r:id="rId9" action="ppaction://hlinksldjump"><a:extLst><a:ext uri="{A12FA001-AC4F-418D-AE19-62706E023703}"><ahyp:hlinkClr xmlns:ahyp="http://schemas.microsoft.com/office/drawing/2018/hyperlinkcolor" val="tx"/></a:ext></a:extLst></a:hlinkClick></a:endParaRPr></a:p></p:txBody></p:sp><p:sp><p:nvSpPr><p:cNvPr id="7" name="Freeform 7"/><p:cNvSpPr/><p:nvPr/></p:nvSpPr><p:spPr><a:xfrm rot="5400000"><a:off x="-3779909" y="-1086192"/><a:ext cx="8733202" cy="2172384"/></a:xfrm><a:custGeom><a:avLst/><a:gdLst/><a:ahLst/><a:cxnLst/><a:rect l="l" t="t" r="r" b="b"/><a:pathLst><a:path w="8733202" h="2172384"><a:moveTo><a:pt x="0" y="0"/></a:moveTo><a:lnTo><a:pt x="8733203" y="0"/></a:lnTo><a:lnTo><a:pt x="8733203" y="2172384"/></a:lnTo><a:lnTo><a:pt x="0" y="2172384"/></a:lnTo><a:lnTo><a:pt x="0" y="0"/></a:lnTo><a:close/></a:path></a:pathLst></a:custGeom><a:blipFill><a:blip r:embed="rId6"><a:extLst><a:ext uri="{96DAC541-7B7A-43D3-8B79-37D633B846F1}"><asvg:svgBlip xmlns:asvg="http://schemas.microsoft.com/office/drawing/2016/SVG/main" r:embed="rId7"/></a:ext></a:extLst></a:blip><a:stretch><a:fillRect/></a:stretch></a:blipFill></p:spPr></p:sp><p:sp><p:nvSpPr><p:cNvPr id="8" name="Freeform 8"/><p:cNvSpPr/><p:nvPr/></p:nvSpPr><p:spPr><a:xfrm rot="5400000"><a:off x="-2610008" y="-1086192"/><a:ext cx="8733202" cy="2172384"/></a:xfrm><a:custGeom><a:avLst/><a:gdLst/><a:ahLst/><a:cxnLst/><a:rect l="l" t="t" r="r" b="b"/><a:pathLst><a:path w="8733202" h="2172384"><a:moveTo><a:pt x="0" y="0"/></a:moveTo><a:lnTo><a:pt x="8733202" y="0"/></a:lnTo><a:lnTo><a:pt x="8733202" y="2172384"/></a:lnTo><a:lnTo><a:pt x="0" y="2172384"/></a:lnTo><a:lnTo><a:pt x="0" y="0"/></a:lnTo><a:close/></a:path></a:pathLst></a:custGeom><a:blipFill><a:blip r:embed="rId6"><a:extLst><a:ext uri="{96DAC541-7B7A-43D3-8B79-37D633B846F1}"><asvg:svgBlip xmlns:asvg="http://schemas.microsoft.com/office/drawing/2016/SVG/main" r:embed="rId7"/></a:ext></a:extLst></a:blip><a:stretch><a:fillRect/></a:stretch></a:blipFill></p:spPr></p:sp><p:sp><p:nvSpPr><p:cNvPr id="9" name="Freeform 9"/><p:cNvSpPr/><p:nvPr/></p:nvSpPr><p:spPr><a:xfrm rot="5400000"><a:off x="-1128654" y="-1086192"/><a:ext cx="8733202" cy="2172384"/></a:xfrm><a:custGeom><a:avLst/><a:gdLst/><a:ahLst/><a:cxnLst/><a:rect l="l" t="t" r="r" b="b"/><a:pathLst><a:path w="8733202" h="2172384"><a:moveTo><a:pt x="0" y="0"/></a:moveTo><a:lnTo><a:pt x="8733202" y="0"/></a:lnTo><a:lnTo><a:pt x="8733202" y="2172384"/></a:lnTo><a:lnTo><a:pt x="0" y="2172384"/></a:lnTo><a:lnTo><a:pt x="0" y="0"/></a:lnTo><a:close/></a:path></a:pathLst></a:custGeom><a:blipFill><a:blip r:embed="rId6"><a:extLst><a:ext uri="{96DAC541-7B7A-43D3-8B79-37D633B846F1}"><asvg:svgBlip xmlns:asvg="http://schemas.microsoft.com/office/drawing/2016/SVG/main" r:embed="rId7"/></a:ext></a:extLst></a:blip><a:stretch><a:fillRect/></a:stretch></a:blipFill></p:spPr></p:sp><p:sp><p:nvSpPr><p:cNvPr id="10" name="Freeform 10"/><p:cNvSpPr/><p:nvPr/></p:nvSpPr><p:spPr><a:xfrm rot="5400000"><a:off x="377191" y="-1026641"/><a:ext cx="8733202" cy="2172384"/></a:xfrm><a:custGeom><a:avLst/><a:gdLst/><a:ahLst/><a:cxnLst/><a:rect l="l" t="t" r="r" b="b"/><a:pathLst><a:path w="8733202" h="2172384"><a:moveTo><a:pt x="0" y="0"/></a:moveTo><a:lnTo><a:pt x="8733202" y="0"/></a:lnTo><a:lnTo><a:pt x="8733202" y="2172384"/></a:lnTo><a:lnTo><a:pt x="0" y="2172384"/></a:lnTo><a:lnTo><a:pt x="0" y="0"/></a:lnTo><a:close/></a:path></a:pathLst></a:custGeom><a:blipFill><a:blip r:embed="rId6"><a:extLst><a:ext uri="{96DAC541-7B7A-43D3-8B79-37D633B846F1}"><asvg:svgBlip xmlns:asvg="http://schemas.microsoft.com/office/drawing/2016/SVG/main" r:embed="rId7"/></a:ext></a:extLst></a:blip><a:stretch><a:fillRect/></a:stretch></a:blipFill></p:spPr></p:sp><p:sp><p:nvSpPr><p:cNvPr id="11" name="Freeform 11"/><p:cNvSpPr/><p:nvPr/></p:nvSpPr><p:spPr><a:xfrm><a:off x="-3181822" y="2625879"/><a:ext cx="8733202" cy="2172384"/></a:xfrm><a:custGeom><a:avLst/><a:gdLst/><a:ahLst/><a:cxnLst/><a:rect l="l" t="t" r="r" b="b"/><a:pathLst><a:path w="8733202" h="2172384"><a:moveTo><a:pt x="0" y="0"/></a:moveTo><a:lnTo><a:pt x="8733202" y="0"/></a:lnTo><a:lnTo><a:pt x="8733202" y="2172384"/></a:lnTo><a:lnTo><a:pt x="0" y="2172384"/></a:lnTo><a:lnTo><a:pt x="0" y="0"/></a:lnTo><a:close/></a:path></a:pathLst></a:custGeom><a:blipFill><a:blip r:embed="rId6"><a:extLst><a:ext uri="{96DAC541-7B7A-43D3-8B79-37D633B846F1}"><asvg:svgBlip xmlns:asvg="http://schemas.microsoft.com/office/drawing/2016/SVG/main" r:embed="rId7"/></a:ext></a:extLst></a:blip><a:stretch><a:fillRect/></a:stretch></a:blipFill></p:spPr></p:sp><p:sp><p:nvSpPr><p:cNvPr id="12" name="TextBox 12"/><p:cNvSpPr txBox="1"/><p:nvPr/></p:nvSpPr><p:spPr><a:xfrm><a:off x="134190" y="173851"/><a:ext cx="5417190" cy="3919220"/></a:xfrm><a:prstGeom prst="rect"><a:avLst/></a:prstGeom></p:spPr><p:txBody><a:bodyPr lIns="0" tIns="0" rIns="0" bIns="0" rtlCol="0" anchor="t"><a:spAutoFit/></a:bodyPr><a:lstStyle/><a:p><a:pPr algn="ctr"><a:lnSpc><a:spcPts val="4480"/></a:lnSpc><a:spcBef><a:spcPct val="0"/></a:spcBef></a:pPr><a:r><a:rPr lang="en-US" sz="3200"><a:solidFill><a:srgbClr val="000000"/></a:solidFill><a:latin typeface=" Avenir Next Arabic"/><a:ea typeface=" Avenir Next Arabic"/><a:cs typeface=" Avenir Next Arabic"/><a:sym typeface=" Avenir Next Arabic"/></a:rPr><a:t>Vocês chegam ao Sanatório Alvorada. O ar é pesado e um cheiro metálico vira o estômago. A porta principal está encostada, também há uma janela no térreo que parece levar ao escritório.</a:t></a:r></a:p></p:txBody></p:sp></p:spTree></p:cSld><p:clrMapOvr><a:masterClrMapping/></p:clrMapOvr><mc:AlternateContent xmlns:mc="http://schemas.openxmlformats.org/markup-compatibility/2006" xmlns:p14="http://schemas.microsoft.com/office/powerpoint/2010/main"><mc:Choice Requires="p14"><p:transition spd="slow" p14:dur="2000" advClick="0"/></mc:Choice><mc:Fallback xmlns=""><p:transition spd="slow" advClick="0"/></mc:Fallback></mc:AlternateContent><p:timing><p:tnLst><p:par><p:cTn id="1" dur="indefinite" restart="never" nodeType="tmRoot"><p:childTnLst><p:seq concurrent="1" nextAc="seek"><p:cTn id="2" dur="indefinite" nodeType="mainSeq"><p:childTnLst><p:par><p:cTn id="3" fill="hold"><p:stCondLst><p:cond delay="indefinite"/><p:cond evt="onBegin" delay="0"><p:tn val="2"/></p:cond></p:stCondLst><p:childTnLst><p:par><p:cTn id="4" fill="hold"><p:stCondLst><p:cond delay="0"/></p:stCondLst><p:childTnLst><p:par><p:cTn id="5" presetID="1" presetClass="mediacall" presetSubtype="0" fill="hold" nodeType="afterEffect"><p:stCondLst><p:cond delay="0"/></p:stCondLst><p:childTnLst><p:cmd type="call" cmd="playFrom(0.0)"><p:cBhvr><p:cTn id="6" dur="1" fill="hold"/><p:tgtEl><p:spTgt spid="16"/></p:tgtEl></p:cBhvr></p:cmd></p:childTnLst></p:cTn></p:par></p:childTnLst></p:cTn></p:par></p:childTnLst></p:cTn></p:par></p:childTnLst></p:cTn><p:prevCondLst><p:cond evt="onPrev" delay="0"><p:tgtEl><p:sldTgt/></p:tgtEl></p:cond></p:prevCondLst><p:nextCondLst><p:cond evt="onNext" delay="0"><p:tgtEl><p:sldTgt/></p:tgtEl></p:cond></p:nextCondLst></p:seq><p:audio><p:cMediaNode numSld="8"><p:cTn id="7" fill="hold" display="0"><p:stCondLst><p:cond delay="indefinite"/></p:stCondLst><p:endCondLst><p:cond evt="onStopAudio" delay="0"><p:tgtEl><p:sldTgt/></p:tgtEl></p:cond></p:endCondLst></p:cTn><p:tgtEl><p:spTgt spid="16"/></p:tgtEl></p:cMediaNode></p:audio></p:childTnLst></p:cTn></p:par></p:tnLst></p:timing></p:sld>